Metadata-Version: 1.0
Name: distributions-mudassar
Version: 0.1
Summary: Gaussian distributions
Home-page: UNKNOWN
Author: Mudassar Hanif
Author-email: mudassarhanif2@gmail.com
License: UNKNOWN
Platform: UNKNOWN
